sigalike/__init__.py
sigalike/py.typed
sigalike/similarity.py
sigalike/utils.py
sigalike-1.0.4.dist-info/LICENSE
sigalike-1.0.4.dist-info/METADATA
sigalike-1.0.4.dist-info/WHEEL
sigalike-1.0.4.dist-info/entry_points.txt
sigalike-1.0.4.dist-info/RECORD
