Metadata-Version: 2.1
Name: sigalike
Version: 1.0.4
Summary: 
Home-page: https://github.com/tjsanti/sigalike
License: Apache-2.0
Author: Trevor Santiago
Requires-Python: >=3.9
Classifier: License :: OSI Approved :: Apache Software License
Classifier: Programming Language :: Python :: 3
Classifier: Programming Language :: Python :: 3.9
Classifier: Programming Language :: Python :: 3.10
Classifier: Programming Language :: Python :: 3.11
Classifier: Programming Language :: Python :: 3.12
Requires-Dist: numpy (>=1.26.4,<2.0.0)
Requires-Dist: rich (>=10.11.0)
Requires-Dist: typing-extensions (>=4.12.2,<5.0.0)
Project-URL: Repository, https://github.com/tjsanti/sigalike
